pygbag/__init__.py
pygbag/__main__.py
pygbag/aio.py
pygbag/app.py
pygbag/dbgserv.py
pygbag/filtering.py
pygbag/fnv.py
pygbag/gateway.py
pygbag/gathering.py
pygbag/html_embed.py
pygbag/mutator.py
pygbag/optimizing.py
pygbag/pack.py
pygbag/testserver.py
pygbag/web.py
pygbag/support/cpythonrc.py
pygbag/support/offline.png
pygbag/support/pygbag_app.py
pygbag/support/pygbag_fsm.py
pygbag/support/pygbag_host.py
pygbag/support/pygbag_ui.py
pygbag/support/pygbag_ux.py
pygbag/support/pyodide.py
pygbag/support/pyscript.py
pygbag/support/readline.new
pygbag/support/readline.py
pygbag/support/typing_extensions.py
pygbag/support/_xterm_parser/__init__.py
pygbag/support/_xterm_parser/_ansi_sequences.py
pygbag/support/_xterm_parser/_context.py
pygbag/support/_xterm_parser/_parser.py
pygbag/support/_xterm_parser/_time.py
pygbag/support/_xterm_parser/_types.py
pygbag/support/_xterm_parser/_xterm_parser.py
pygbag/support/_xterm_parser/case.py
pygbag/support/_xterm_parser/events.py
pygbag/support/_xterm_parser/geometry.py
pygbag/support/_xterm_parser/keys.py
pygbag/support/_xterm_parser/message.py
pygbag/support/_xterm_parser/messages.py
pygbag/support/cross/__EMSCRIPTEN__.py
pygbag/support/cross/__WASM__.py
pygbag/support/cross/aio/__init__.py
pygbag/support/cross/aio/atexit.py
pygbag/support/cross/aio/clock.py
pygbag/support/cross/aio/cross.py
pygbag/support/cross/aio/fetch.py
pygbag/support/cross/aio/filelike.py
pygbag/support/cross/aio/gthread.py
pygbag/support/cross/aio/pep0723.py
pygbag/support/cross/aio/prepro.py
pygbag/support/cross/aio/recycle.py
pygbag/support/cross/aio/repl.py
pygbag/support/cross/aio/toplevel.py
pygbag/support/cross/aio/tracer.py
pygbag/support/cross/tomllib/__init__.py
pygbag/support/cross/tomllib/_parser.py
pygbag/support/cross/tomllib/_re.py
pygbag/support/cross/tomllib/_types.py
pygbag-0.9.2.dist-info/LICENSE
pygbag-0.9.2.dist-info/METADATA
pygbag-0.9.2.dist-info/WHEEL
pygbag-0.9.2.dist-info/entry_points.txt
pygbag-0.9.2.dist-info/top_level.txt
pygbag-0.9.2.dist-info/RECORD
