Metadata-Version: 2.1
Name: pygbag
Version: 0.9.2
Summary: package and run python/pygame-ce wasm (and more) directly in modern web browsers.
Home-page: https://pygame-web.github.io/
Author: Paul Peny
Project-URL: Wiki, https://pygame-web.github.io/
Project-URL: Bug Tracker, https://github.com/pygame-web/pygbag/issues
Project-URL: Source Code, https://github.com/pygame-web/pygbag
Project-URL: Project Page, https://github.com/pygame-web
Classifier: Programming Language :: Python :: 3
Classifier: License :: OSI Approved :: MIT License
Classifier: Operating System :: OS Independent
Requires-Python: >=3.8
License-File: LICENSE
Provides-Extra: sim
Requires-Dist: aioconsole; extra == "sim"
Requires-Dist: aiohttp; extra == "sim"
Requires-Dist: asyncio_socks_server; extra == "sim"
